greensms/__init__.py
greensms/client.py
greensms/constants.py
greensms/api/__init__.py
greensms/api/module.py
greensms/api/module_loader.py
greensms/api/modules.py
greensms/api/schema.py
greensms/http/__init__.py
greensms/http/error.py
greensms/http/rest.py
greensms/utils/__init__.py
greensms/utils/attr_dict.py
greensms/utils/cascade_validator.py
greensms/utils/dict.py
greensms/utils/url.py
greensms/utils/validator.py
greensms/utils/version.py
greensms-2.0.1.dist-info/METADATA
greensms-2.0.1.dist-info/WHEEL
greensms-2.0.1.dist-info/top_level.txt
greensms-2.0.1.dist-info/RECORD
