Metadata-Version: 2.1
Name: greensms
Version: 2.0.1
Summary: GREENSMS API: SMS, Call, Voice, VK, WhatsApp, Viber, HLR, Pay
Home-page: https://github.com/greensms-ru/greensms-python
Author: GreenSMS
Author-email: support@greensms.ru
License: MIT
Keywords: greensms,sms,sms-api,call-for-code,rest,api,viber,whatsapp
Classifier: Development Status :: 3 - Alpha
Classifier: Intended Audience :: Developers
Classifier: License :: OSI Approved :: MIT License
Classifier: Programming Language :: Python :: 2.7
Classifier: Programming Language :: Python :: 3.4
Classifier: Programming Language :: Python :: 3.5
Classifier: Programming Language :: Python :: 3.6
Classifier: Programming Language :: Python :: 3.7
Classifier: Programming Language :: Python :: 3.8
Classifier: Programming Language :: Python :: 3.9
Classifier: Programming Language :: Python :: 3.10
Classifier: Programming Language :: Python :: 3.11
Classifier: Topic :: Software Development :: Libraries :: Python Modules
Requires-Dist: requests
Requires-Dist: six
Requires-Dist: twine
Requires-Dist: cerberus
Requires-Dist: pyhumps
Requires-Dist: requests[security] (>=2.0.0) ; python_version<"3.0"
Requires-Dist: pyhumps (==3.0.2) ; python_version<"3.0"
Requires-Dist: requests (>=2.0.0) ; python_version>="3.0"
Requires-Dist: pyhumps (>=3.5.0) ; python_version>="3.0"
